reblob/__init__.py
reblob/__main__.py
reblob/__version__.py
reblob/dom_extract.py
reblob-0.0.2.dist-info/LICENSE
reblob-0.0.2.dist-info/METADATA
reblob-0.0.2.dist-info/WHEEL
reblob-0.0.2.dist-info/entry_points.txt
reblob-0.0.2.dist-info/top_level.txt
reblob-0.0.2.dist-info/RECORD
